[
  {
    "category": "Best Picture",
    "year": "2002",
    "nominees": [
      "Chicago"
    ],
    "movies": [
      {
        "title": "Chicago",
        "tmdb_id": 1574,
        "imdb_id": "tt0299658"
      }
    ],
    "won": true
  },
  {
    "category": "Best Picture",
    "year": "2002",
    "nominees": [
      "Gangs of New York"
    ],
    "movies": [
      {
        "title": "Gangs of New York",
        "tmdb_id": 3131,
        "imdb_id": "tt0217505"
      }
    ],
    "won": false
  },
  {
    "category": "Best Picture",
    "year": "2002",
    "nominees": [
      "The Hours"
    ],
    "movies": [
      {
        "title": "The Hours",
        "tmdb_id": 590,
        "imdb_id": "tt0274558"
      }
    ],
    "won": false
  },
  {
    "category": "Best Picture",
    "year": "2002",
    "nominees": [
      "The Lord of the Rings: The Two Towers"
    ],
    "movies": [
      {
        "title": "The Lord of the Rings: The Two Towers",
        "tmdb_id": 121,
        "imdb_id": "tt0167261"
      }
    ],
    "won": false
  },
  {
    "category": "Best Picture",
    "year": "2002",
    "nominees": [
      "The Pianist"
    ],
    "movies": [
      {
        "title": "The Pianist",
        "tmdb_id": 423,
        "imdb_id": "tt0253474"
      }
    ],
    "won": false
  },
  {
    "category": "Best Actor",
    "year": "2002",
    "nominees": [
      "Adrien Brody"
    ],
    "movies": [
      {
        "title": "The Pianist",
        "tmdb_id": 423,
        "imdb_id": "tt0253474"
      }
    ],
    "won": true
  },
  {
    "category": "Best Actor",
    "year": "2002",
    "nominees": [
      "Nicolas Cage"
    ],
    "movies": [
      {
        "title": "Adaptation.",
        "tmdb_id": 2757,
        "imdb_id": "tt0268126"
      }
    ],
    "won": false
  },
  {
    "category": "Best Actor",
    "year": "2002",
    "nominees": [
      "Michael Caine"
    ],
    "movies": [
      {
        "title": "The Quiet American",
        "tmdb_id": 8198,
        "imdb_id": "tt0258068"
      }
    ],
    "won": false
  },
  {
    "category": "Best Actor",
    "year": "2002",
    "nominees": [
      "Daniel Day-Lewis"
    ],
    "movies": [
      {
        "title": "Gangs of New York",
        "tmdb_id": 3131,
        "imdb_id": "tt0217505"
      }
    ],
    "won": false
  },
  {
    "category": "Best Actor",
    "year": "2002",
    "nominees": [
      "Jack Nicholson"
    ],
    "movies": [
      {
        "title": "About Schmidt",
        "tmdb_id": 2755,
        "imdb_id": "tt0257360"
      }
    ],
    "won": false
  },
  {
    "category": "Best Actress",
    "year": "2002",
    "nominees": [
      "Nicole Kidman"
    ],
    "movies": [
      {
        "title": "The Hours",
        "tmdb_id": 590,
        "imdb_id": "tt0274558"
      }
    ],
    "won": true
  },
  {
    "category": "Best Actress",
    "year": "2002",
    "nominees": [
      "Salma Hayek"
    ],
    "movies": [
      {
        "title": "Frida",
        "tmdb_id": 1360,
        "imdb_id": "tt0120679"
      }
    ],
    "won": false
  },
  {
    "category": "Best Actress",
    "year": "2002",
    "nominees": [
      "Diane Lane"
    ],
    "movies": [
      {
        "title": "Unfaithful",
        "tmdb_id": 2251,
        "imdb_id": "tt0250797"
      }
    ],
    "won": false
  },
  {
    "category": "Best Actress",
    "year": "2002",
    "nominees": [
      "Julianne Moore"
    ],
    "movies": [
      {
        "title": "Far from Heaven",
        "tmdb_id": 10712,
        "imdb_id": "tt0297884"
      }
    ],
    "won": false
  },
  {
    "category": "Best Actress",
    "year": "2002",
    "nominees": [
      "Renee Zellweger"
    ],
    "movies": [
      {
        "title": "Chicago",
        "tmdb_id": 1574,
        "imdb_id": "tt0299658"
      }
    ],
    "won": false
  },
  {
    "category": "Best Supporting Actor",
    "year": "2002",
    "nominees": [
      "Chris Cooper"
    ],
    "movies": [
      {
        "title": "Adaptation.",
        "tmdb_id": 2757,
        "imdb_id": "tt0268126"
      }
    ],
    "won": true
  },
  {
    "category": "Best Supporting Actor",
    "year": "2002",
    "nominees": [
      "Ed Harris"
    ],
    "movies": [
      {
        "title": "The Hours",
        "tmdb_id": 590,
        "imdb_id": "tt0274558"
      }
    ],
    "won": false
  },
  {
    "category": "Best Supporting Actor",
    "year": "2002",
    "nominees": [
      "Paul Newman"
    ],
    "movies": [
      {
        "title": "Road to Perdition",
        "tmdb_id": 4147,
        "imdb_id": "tt0257044"
      }
    ],
    "won": false
  },
  {
    "category": "Best Supporting Actor",
    "year": "2002",
    "nominees": [
      "John C. Reilly"
    ],
    "movies": [
      {
        "title": "Chicago",
        "tmdb_id": 1574,
        "imdb_id": "tt0299658"
      }
    ],
    "won": false
  },
  {
    "category": "Best Supporting Actor",
    "year": "2002",
    "nominees": [
      "Christopher Walken"
    ],
    "movies": [
      {
        "title": "Catch Me If You Can",
        "tmdb_id": 640,
        "imdb_id": "tt0264464"
      }
    ],
    "won": false
  },
  {
    "category": "Best Supporting Actress",
    "year": "2002",
    "nominees": [
      "Catherine Zeta-Jones"
    ],
    "movies": [
      {
        "title": "Chicago",
        "tmdb_id": 1574,
        "imdb_id": "tt0299658"
      }
    ],
    "won": true
  },
  {
    "category": "Best Supporting Actress",
    "year": "2002",
    "nominees": [
      "Kathy Bates"
    ],
    "movies": [
      {
        "title": "About Schmidt",
        "tmdb_id": 2755,
        "imdb_id": "tt0257360"
      }
    ],
    "won": false
  },
  {
    "category": "Best Supporting Actress",
    "year": "2002",
    "nominees": [
      "Queen Latifah"
    ],
    "movies": [
      {
        "title": "Chicago",
        "tmdb_id": 1574,
        "imdb_id": "tt0299658"
      }
    ],
    "won": false
  },
  {
    "category": "Best Supporting Actress",
    "year": "2002",
    "nominees": [
      "Julianne Moore"
    ],
    "movies": [
      {
        "title": "The Hours",
        "tmdb_id": 590,
        "imdb_id": "tt0274558"
      }
    ],
    "won": false
  },
  {
    "category": "Best Supporting Actress",
    "year": "2002",
    "nominees": [
      "Meryl Streep"
    ],
    "movies": [
      {
        "title": "Adaptation.",
        "tmdb_id": 2757,
        "imdb_id": "tt0268126"
      }
    ],
    "won": false
  },
  {
    "category": "Best Director",
    "year": "2002",
    "nominees": [
      "Roman Polanski"
    ],
    "movies": [
      {
        "title": "The Pianist",
        "tmdb_id": 423,
        "imdb_id": "tt0253474"
      }
    ],
    "won": true
  },
  {
    "category": "Best Director",
    "year": "2002",
    "nominees": [
      "Pedro Almodovar"
    ],
    "movies": [
      {
        "title": "Talk to Her",
        "tmdb_id": 64,
        "imdb_id": "tt0287467"
      }
    ],
    "won": false
  },
  {
    "category": "Best Director",
    "year": "2002",
    "nominees": [
      "Stephen Daldry"
    ],
    "movies": [
      {
        "title": "The Hours",
        "tmdb_id": 590,
        "imdb_id": "tt0274558"
      }
    ],
    "won": false
  },
  {
    "category": "Best Director",
    "year": "2002",
    "nominees": [
      "Rob Marshall"
    ],
    "movies": [
      {
        "title": "Chicago",
        "tmdb_id": 1574,
        "imdb_id": "tt0299658"
      }
    ],
    "won": false
  },
  {
    "category": "Best Director",
    "year": "2002",
    "nominees": [
      "Martin Scorsese"
    ],
    "movies": [
      {
        "title": "Gangs of New York",
        "tmdb_id": 3131,
        "imdb_id": "tt0217505"
      }
    ],
    "won": false
  },
  {
    "category": "Best Adapted Screenplay",
    "year": "2002",
    "nominees": [
      "Ronald Harwood"
    ],
    "movies": [
      {
        "title": "The Pianist",
        "tmdb_id": 423,
        "imdb_id": "tt0253474"
      }
    ],
    "won": true
  },
  {
    "category": "Best Adapted Screenplay",
    "year": "2002",
    "nominees": [
      "Peter Hedges",
      "Chris Weitz",
      "Paul Weitz"
    ],
    "movies": [
      {
        "title": "About a Boy",
        "tmdb_id": 245,
        "imdb_id": "tt0276751"
      }
    ],
    "won": false
  },
  {
    "category": "Best Adapted Screenplay",
    "year": "2002",
    "nominees": [
      "Charlie Kaufman",
      "Donald Kaufman"
    ],
    "movies": [
      {
        "title": "Adaptation.",
        "tmdb_id": 2757,
        "imdb_id": "tt0268126"
      }
    ],
    "won": false
  },
  {
    "category": "Best Adapted Screenplay",
    "year": "2002",
    "nominees": [
      "Bill Condon"
    ],
    "movies": [
      {
        "title": "Chicago",
        "tmdb_id": 1574,
        "imdb_id": "tt0299658"
      }
    ],
    "won": false
  },
  {
    "category": "Best Adapted Screenplay",
    "year": "2002",
    "nominees": [
      "David Hare"
    ],
    "movies": [
      {
        "title": "The Hours",
        "tmdb_id": 590,
        "imdb_id": "tt0274558"
      }
    ],
    "won": false
  },
  {
    "category": "Best Original Screenplay",
    "year": "2002",
    "nominees": [
      "Pedro Almodovar"
    ],
    "movies": [
      {
        "title": "Talk to Her",
        "tmdb_id": 64,
        "imdb_id": "tt0287467"
      }
    ],
    "won": true
  },
  {
    "category": "Best Original Screenplay",
    "year": "2002",
    "nominees": [
      "Todd Haynes"
    ],
    "movies": [
      {
        "title": "Far from Heaven",
        "tmdb_id": 10712,
        "imdb_id": "tt0297884"
      }
    ],
    "won": false
  },
  {
    "category": "Best Original Screenplay",
    "year": "2002",
    "nominees": [
      "Jay Cocks",
      "Kenneth Lonergan",
      "Steven Zaillian"
    ],
    "movies": [
      {
        "title": "Gangs of New York",
        "tmdb_id": 3131,
        "imdb_id": "tt0217505"
      }
    ],
    "won": false
  },
  {
    "category": "Best Original Screenplay",
    "year": "2002",
    "nominees": [
      "Nia Vardalos"
    ],
    "movies": [
      {
        "title": "My Big Fat Greek Wedding",
        "tmdb_id": 8346,
        "imdb_id": "tt0259446"
      }
    ],
    "won": false
  },
  {
    "category": "Best Original Screenplay",
    "year": "2002",
    "nominees": [
      "Carlos Cuarón",
      "Alfonso Cuaron"
    ],
    "movies": [
      {
        "title": "Y Tu Mamá También",
        "tmdb_id": 1391,
        "imdb_id": "tt0245574"
      }
    ],
    "won": false
  },
  {
    "category": "Best Score",
    "year": "2002",
    "nominees": [
      "Elliot Goldenthal"
    ],
    "movies": [
      {
        "title": "Frida",
        "tmdb_id": 1360,
        "imdb_id": "tt0120679"
      }
    ],
    "won": true
  },
  {
    "category": "Best Score",
    "year": "2002",
    "nominees": [
      "John Williams"
    ],
    "movies": [
      {
        "title": "Catch Me If You Can",
        "tmdb_id": 640,
        "imdb_id": "tt0264464"
      }
    ],
    "won": false
  },
  {
    "category": "Best Score",
    "year": "2002",
    "nominees": [
      "Elmer Bernstein"
    ],
    "movies": [
      {
        "title": "Far from Heaven",
        "tmdb_id": 10712,
        "imdb_id": "tt0297884"
      }
    ],
    "won": false
  },
  {
    "category": "Best Score",
    "year": "2002",
    "nominees": [
      "Philip Glass"
    ],
    "movies": [
      {
        "title": "The Hours",
        "tmdb_id": 590,
        "imdb_id": "tt0274558"
      }
    ],
    "won": false
  },
  {
    "category": "Best Score",
    "year": "2002",
    "nominees": [
      "Thomas Newman"
    ],
    "movies": [
      {
        "title": "Road to Perdition",
        "tmdb_id": 4147,
        "imdb_id": "tt0257044"
      }
    ],
    "won": false
  },
  {
    "category": "Best Original Song",
    "year": "2002",
    "nominees": [
      "Lose Yourself"
    ],
    "movies": [
      {
        "title": "8 Mile",
        "tmdb_id": 65,
        "imdb_id": "tt0298203"
      }
    ],
    "won": true
  },
  {
    "category": "Best Original Song",
    "year": "2002",
    "nominees": [
      "I Move On"
    ],
    "movies": [
      {
        "title": "Chicago",
        "tmdb_id": 1574,
        "imdb_id": "tt0299658"
      }
    ],
    "won": false
  },
  {
    "category": "Best Original Song",
    "year": "2002",
    "nominees": [
      "Burn It Blue"
    ],
    "movies": [
      {
        "title": "Frida",
        "tmdb_id": 1360,
        "imdb_id": "tt0120679"
      }
    ],
    "won": false
  },
  {
    "category": "Best Original Song",
    "year": "2002",
    "nominees": [
      "The Hands That Built America"
    ],
    "movies": [
      {
        "title": "Gangs of New York",
        "tmdb_id": 3131,
        "imdb_id": "tt0217505"
      }
    ],
    "won": false
  },
  {
    "category": "Best Original Song",
    "year": "2002",
    "nominees": [
      "Father",
      "Daughter"
    ],
    "movies": [
      {
        "title": "The Wild Thornberrys Movie",
        "tmdb_id": 14317,
        "imdb_id": "tt0282120"
      }
    ],
    "won": false
  },
  {
    "category": "Best International Feature Film",
    "year": "2002",
    "nominees": [
      "Nowhere in Africa"
    ],
    "movies": [
      {
        "title": "Nowhere in Africa",
        "tmdb_id": 1591,
        "imdb_id": "tt0161860"
      }
    ],
    "won": true
  },
  {
    "category": "Best International Feature Film",
    "year": "2002",
    "nominees": [
      "The Crime of Padre Amaro"
    ],
    "movies": [
      {
        "title": "The Crime of Padre Amaro",
        "tmdb_id": 542,
        "imdb_id": "tt0313196"
      }
    ],
    "won": false
  },
  {
    "category": "Best International Feature Film",
    "year": "2002",
    "nominees": [
      "HERO"
    ],
    "movies": [
      {
        "title": "HERO",
        "tmdb_id": 782713,
        "imdb_id": null
      }
    ],
    "won": false
  },
  {
    "category": "Best International Feature Film",
    "year": "2002",
    "nominees": [
      "The Man Without a Past"
    ],
    "movies": [
      {
        "title": "The Man Without a Past",
        "tmdb_id": 7294,
        "imdb_id": "tt0311519"
      }
    ],
    "won": false
  },
  {
    "category": "Best International Feature Film",
    "year": "2002",
    "nominees": [
      "Zus & Zo"
    ],
    "movies": [
      {
        "title": "Zus & Zo",
        "tmdb_id": 16539,
        "imdb_id": "tt0245157"
      }
    ],
    "won": false
  },
  {
    "category": "Best Documentary Feature",
    "year": "2002",
    "nominees": [
      "Bowling for Columbine"
    ],
    "movies": [
      {
        "title": "Bowling for Columbine",
        "tmdb_id": 1430,
        "imdb_id": "tt0310793"
      }
    ],
    "won": true
  },
  {
    "category": "Best Documentary Feature",
    "year": "2002",
    "nominees": [
      "Daughter From Danang"
    ],
    "movies": [
      {
        "title": "Daughter From Danang",
        "tmdb_id": 67232,
        "imdb_id": "tt0303281"
      }
    ],
    "won": false
  },
  {
    "category": "Best Documentary Feature",
    "year": "2002",
    "nominees": [
      "Prisoner of Paradise"
    ],
    "movies": [
      {
        "title": "Prisoner of Paradise",
        "tmdb_id": 112902,
        "imdb_id": "tt0316013"
      }
    ],
    "won": false
  },
  {
    "category": "Best Documentary Feature",
    "year": "2002",
    "nominees": [
      "Spellbound"
    ],
    "movies": [
      {
        "title": "Spellbound",
        "tmdb_id": 16636,
        "imdb_id": "tt0334405"
      }
    ],
    "won": false
  },
  {
    "category": "Best Documentary Feature",
    "year": "2002",
    "nominees": [
      "Winged Migration"
    ],
    "movies": [
      {
        "title": "Winged Migration",
        "tmdb_id": 11516,
        "imdb_id": "tt0301727"
      }
    ],
    "won": false
  },
  {
    "category": "Best Documentary Short",
    "year": "2002",
    "nominees": [
      "Twin Towers"
    ],
    "movies": [
      {
        "title": "Twin Towers",
        "tmdb_id": 194819,
        "imdb_id": "tt0344503"
      }
    ],
    "won": true
  },
  {
    "category": "Best Documentary Short",
    "year": "2002",
    "nominees": [
      "The Collector of Bedford Street"
    ],
    "movies": [
      {
        "title": "The Collector of Bedford Street",
        "tmdb_id": 244982,
        "imdb_id": "tt0325193"
      }
    ],
    "won": false
  },
  {
    "category": "Best Documentary Short",
    "year": "2002",
    "nominees": [
      "Mighty Times: The Legacy of Rosa Parks"
    ],
    "movies": [
      {
        "title": "Mighty Times: The Legacy of Rosa Parks",
        "tmdb_id": 244983,
        "imdb_id": "tt0353737"
      }
    ],
    "won": false
  },
  {
    "category": "Best Documentary Short",
    "year": "2002",
    "nominees": [
      "Why Can't We Be a Family Again?"
    ],
    "movies": [
      {
        "title": "Why Can't We Be a Family Again?",
        "tmdb_id": 244984,
        "imdb_id": "tt0344563"
      }
    ],
    "won": false
  },
  {
    "category": "Best Animated Feature",
    "year": "2002",
    "nominees": [
      "Spirited Away"
    ],
    "movies": [
      {
        "title": "Spirited Away",
        "tmdb_id": 129,
        "imdb_id": "tt0245429"
      }
    ],
    "won": true
  },
  {
    "category": "Best Animated Feature",
    "year": "2002",
    "nominees": [
      "Ice Age"
    ],
    "movies": [
      {
        "title": "Ice Age",
        "tmdb_id": 425,
        "imdb_id": "tt0268380"
      }
    ],
    "won": false
  },
  {
    "category": "Best Animated Feature",
    "year": "2002",
    "nominees": [
      "Lilo & Stitch"
    ],
    "movies": [
      {
        "title": "Lilo & Stitch",
        "tmdb_id": 11544,
        "imdb_id": "tt0275847"
      }
    ],
    "won": false
  },
  {
    "category": "Best Animated Feature",
    "year": "2002",
    "nominees": [
      "Spirit: Stallion of the Cimarron"
    ],
    "movies": [
      {
        "title": "Spirit: Stallion of the Cimarron",
        "tmdb_id": 9023,
        "imdb_id": "tt0166813"
      }
    ],
    "won": false
  },
  {
    "category": "Best Animated Feature",
    "year": "2002",
    "nominees": [
      "Treasure Planet"
    ],
    "movies": [
      {
        "title": "Treasure Planet",
        "tmdb_id": 9016,
        "imdb_id": "tt0133240"
      }
    ],
    "won": false
  },
  {
    "category": "Best Animated Short",
    "year": "2002",
    "nominees": [
      "The ChubbChubbs!"
    ],
    "movies": [
      {
        "title": "The ChubbChubbs!",
        "tmdb_id": 27042,
        "imdb_id": "tt0331218"
      }
    ],
    "won": true
  },
  {
    "category": "Best Animated Short",
    "year": "2002",
    "nominees": [
      "Mount Head"
    ],
    "movies": [
      {
        "title": "Mount Head",
        "tmdb_id": 36072,
        "imdb_id": "tt0351382"
      }
    ],
    "won": false
  },
  {
    "category": "Best Animated Short",
    "year": "2002",
    "nominees": [
      "Rocks"
    ],
    "movies": [
      {
        "title": "Rocks",
        "tmdb_id": 37060,
        "imdb_id": "tt0330801"
      }
    ],
    "won": false
  },
  {
    "category": "Best Animated Short",
    "year": "2002",
    "nominees": [
      "The Cathedral"
    ],
    "movies": [
      {
        "title": "The Cathedral",
        "tmdb_id": 15990,
        "imdb_id": "tt0351167"
      }
    ],
    "won": false
  },
  {
    "category": "Best Animated Short",
    "year": "2002",
    "nominees": [
      "Mike's New Car"
    ],
    "movies": [
      {
        "title": "Mike's New Car",
        "tmdb_id": 13931,
        "imdb_id": "tt0323250"
      }
    ],
    "won": false
  },
  {
    "category": "Best Live Action Short (Comedy or One Reel or Regular)",
    "year": "2002",
    "nominees": [
      "This Charming Man"
    ],
    "movies": [
      {
        "title": "This Charming Man",
        "tmdb_id": 115479,
        "imdb_id": "tt0340071"
      }
    ],
    "won": true
  },
  {
    "category": "Best Live Action Short (Comedy or One Reel or Regular)",
    "year": "2002",
    "nominees": [
      "Gridlock"
    ],
    "movies": [
      {
        "title": "Gridlock",
        "tmdb_id": 121966,
        "imdb_id": "tt0281850"
      }
    ],
    "won": false
  },
  {
    "category": "Best Live Action Short (Comedy or One Reel or Regular)",
    "year": "2002",
    "nominees": [
      "I'll Wait for the Next One..."
    ],
    "movies": [
      {
        "title": "I'll Wait for the Next One...",
        "tmdb_id": 162657,
        "imdb_id": "tt0325638"
      }
    ],
    "won": false
  },
  {
    "category": "Best Live Action Short (Comedy or One Reel or Regular)",
    "year": "2002",
    "nominees": [
      "Inja"
    ],
    "movies": [
      {
        "title": "Inja",
        "tmdb_id": 165664,
        "imdb_id": "tt0303350"
      }
    ],
    "won": false
  },
  {
    "category": "Best Live Action Short (Comedy or One Reel or Regular)",
    "year": "2002",
    "nominees": [
      "Johnny Flynton"
    ],
    "movies": [
      {
        "title": "Johnny Flynton",
        "tmdb_id": 244981,
        "imdb_id": "tt0329245"
      }
    ],
    "won": false
  },
  {
    "category": "Best Production Design (Color)",
    "year": "2002",
    "nominees": [
      "John Myhre",
      "Gordon Sim"
    ],
    "movies": [
      {
        "title": "Chicago",
        "tmdb_id": 1574,
        "imdb_id": "tt0299658"
      }
    ],
    "won": true
  },
  {
    "category": "Best Production Design (Color)",
    "year": "2002",
    "nominees": [
      "Felipe Fernandez del Paso",
      "Hania Robledo"
    ],
    "movies": [
      {
        "title": "Frida",
        "tmdb_id": 1360,
        "imdb_id": "tt0120679"
      }
    ],
    "won": false
  },
  {
    "category": "Best Production Design (Color)",
    "year": "2002",
    "nominees": [
      "Dante Ferretti",
      "Francesca Lo Schiavo"
    ],
    "movies": [
      {
        "title": "Gangs of New York",
        "tmdb_id": 3131,
        "imdb_id": "tt0217505"
      }
    ],
    "won": false
  },
  {
    "category": "Best Production Design (Color)",
    "year": "2002",
    "nominees": [
      "Grant Major",
      "Dan Hennah",
      "Alan Lee"
    ],
    "movies": [
      {
        "title": "The Lord of the Rings: The Two Towers",
        "tmdb_id": 121,
        "imdb_id": "tt0167261"
      }
    ],
    "won": false
  },
  {
    "category": "Best Production Design (Color)",
    "year": "2002",
    "nominees": [
      "Dennis Gassner",
      "Nancy Haigh"
    ],
    "movies": [
      {
        "title": "Road to Perdition",
        "tmdb_id": 4147,
        "imdb_id": "tt0257044"
      }
    ],
    "won": false
  },
  {
    "category": "Best Cinematography (Color)",
    "year": "2002",
    "nominees": [
      "Conrad Hall"
    ],
    "movies": [
      {
        "title": "Road to Perdition",
        "tmdb_id": 4147,
        "imdb_id": "tt0257044"
      }
    ],
    "won": true
  },
  {
    "category": "Best Cinematography (Color)",
    "year": "2002",
    "nominees": [
      "Dion Beebe"
    ],
    "movies": [
      {
        "title": "Chicago",
        "tmdb_id": 1574,
        "imdb_id": "tt0299658"
      }
    ],
    "won": false
  },
  {
    "category": "Best Cinematography (Color)",
    "year": "2002",
    "nominees": [
      "Edward Lachman"
    ],
    "movies": [
      {
        "title": "Far from Heaven",
        "tmdb_id": 10712,
        "imdb_id": "tt0297884"
      }
    ],
    "won": false
  },
  {
    "category": "Best Cinematography (Color)",
    "year": "2002",
    "nominees": [
      "Michael Ballhaus"
    ],
    "movies": [
      {
        "title": "Gangs of New York",
        "tmdb_id": 3131,
        "imdb_id": "tt0217505"
      }
    ],
    "won": false
  },
  {
    "category": "Best Cinematography (Color)",
    "year": "2002",
    "nominees": [
      "Pawel Edelman"
    ],
    "movies": [
      {
        "title": "The Pianist",
        "tmdb_id": 423,
        "imdb_id": "tt0253474"
      }
    ],
    "won": false
  },
  {
    "category": "Best Film Editing",
    "year": "2002",
    "nominees": [
      "Martin Walsh"
    ],
    "movies": [
      {
        "title": "Chicago",
        "tmdb_id": 1574,
        "imdb_id": "tt0299658"
      }
    ],
    "won": true
  },
  {
    "category": "Best Film Editing",
    "year": "2002",
    "nominees": [
      "Thelma Schoonmaker"
    ],
    "movies": [
      {
        "title": "Gangs of New York",
        "tmdb_id": 3131,
        "imdb_id": "tt0217505"
      }
    ],
    "won": false
  },
  {
    "category": "Best Film Editing",
    "year": "2002",
    "nominees": [
      "Peter Boyle"
    ],
    "movies": [
      {
        "title": "The Hours",
        "tmdb_id": 590,
        "imdb_id": "tt0274558"
      }
    ],
    "won": false
  },
  {
    "category": "Best Film Editing",
    "year": "2002",
    "nominees": [
      "Michael Horton"
    ],
    "movies": [
      {
        "title": "The Lord of the Rings: The Two Towers",
        "tmdb_id": 121,
        "imdb_id": "tt0167261"
      }
    ],
    "won": false
  },
  {
    "category": "Best Film Editing",
    "year": "2002",
    "nominees": [
      "Herve de Luze"
    ],
    "movies": [
      {
        "title": "The Pianist",
        "tmdb_id": 423,
        "imdb_id": "tt0253474"
      }
    ],
    "won": false
  },
  {
    "category": "Best Visual/Special Effects",
    "year": "2002",
    "nominees": [
      "Jim Rygiel",
      "Joe Letteri",
      "Randall William Cook",
      "Alex Funke"
    ],
    "movies": [
      {
        "title": "The Lord of the Rings: The Two Towers",
        "tmdb_id": 121,
        "imdb_id": "tt0167261"
      }
    ],
    "won": true
  },
  {
    "category": "Best Visual/Special Effects",
    "year": "2002",
    "nominees": [
      "John Dykstra",
      "Scott Stokdyk",
      "Anthony LaMolinara",
      "John Frazier"
    ],
    "movies": [
      {
        "title": "Spider-Man",
        "tmdb_id": 557,
        "imdb_id": "tt0145487"
      }
    ],
    "won": false
  },
  {
    "category": "Best Visual/Special Effects",
    "year": "2002",
    "nominees": [
      "Rob Coleman",
      "Pablo Helman",
      "John Knoll",
      "Ben Snow"
    ],
    "movies": [
      {
        "title": "Star Wars: Episode II - Attack of the Clones",
        "tmdb_id": 1894,
        "imdb_id": "tt0121765"
      }
    ],
    "won": false
  },
  {
    "category": "Best Sound Mixing",
    "year": "2002",
    "nominees": [
      "Michael Minkler",
      "Dominick Tavella",
      "David Lee"
    ],
    "movies": [
      {
        "title": "Chicago",
        "tmdb_id": 1574,
        "imdb_id": "tt0299658"
      }
    ],
    "won": true
  },
  {
    "category": "Best Sound Mixing",
    "year": "2002",
    "nominees": [
      "Tom Fleischman",
      "Eugene Gearty",
      "Ivan Sharrock"
    ],
    "movies": [
      {
        "title": "Gangs of New York",
        "tmdb_id": 3131,
        "imdb_id": "tt0217505"
      }
    ],
    "won": false
  },
  {
    "category": "Best Sound Mixing",
    "year": "2002",
    "nominees": [
      "Christopher Boyes",
      "Michael Semanick",
      "Michael Hedges",
      "Hammond Peek"
    ],
    "movies": [
      {
        "title": "The Lord of the Rings: The Two Towers",
        "tmdb_id": 121,
        "imdb_id": "tt0167261"
      }
    ],
    "won": false
  },
  {
    "category": "Best Sound Mixing",
    "year": "2002",
    "nominees": [
      "Scott Millan",
      "Bob Beemer",
      "John Pritchett"
    ],
    "movies": [
      {
        "title": "Road to Perdition",
        "tmdb_id": 4147,
        "imdb_id": "tt0257044"
      }
    ],
    "won": false
  },
  {
    "category": "Best Sound Mixing",
    "year": "2002",
    "nominees": [
      "Kevin O'Connell",
      "Greg P. Russell",
      "Ed Novick"
    ],
    "movies": [
      {
        "title": "Spider-Man",
        "tmdb_id": 557,
        "imdb_id": "tt0145487"
      }
    ],
    "won": false
  },
  {
    "category": "Best Sound Editing",
    "year": "2002",
    "nominees": [
      "Mike Hopkins",
      "Ethan Van der Ryn"
    ],
    "movies": [
      {
        "title": "The Lord of the Rings: The Two Towers",
        "tmdb_id": 121,
        "imdb_id": "tt0167261"
      }
    ],
    "won": true
  },
  {
    "category": "Best Sound Editing",
    "year": "2002",
    "nominees": [
      "Richard Hymns",
      "Gary Rydstrom"
    ],
    "movies": [
      {
        "title": "Minority Report",
        "tmdb_id": 180,
        "imdb_id": "tt0181689"
      }
    ],
    "won": false
  },
  {
    "category": "Best Sound Editing",
    "year": "2002",
    "nominees": [
      "Scott Hecker"
    ],
    "movies": [
      {
        "title": "Road to Perdition",
        "tmdb_id": 4147,
        "imdb_id": "tt0257044"
      }
    ],
    "won": false
  },
  {
    "category": "Best Makeup and Hairstyling",
    "year": "2002",
    "nominees": [
      "John Jackson",
      "Beatrice De Alba"
    ],
    "movies": [
      {
        "title": "Frida",
        "tmdb_id": 1360,
        "imdb_id": "tt0120679"
      }
    ],
    "won": true
  },
  {
    "category": "Best Makeup and Hairstyling",
    "year": "2002",
    "nominees": [
      "John M. Elliott Jr.",
      "Barbara Lorenz"
    ],
    "movies": [
      {
        "title": "The Time Machine",
        "tmdb_id": 2135,
        "imdb_id": "tt0268695"
      }
    ],
    "won": false
  },
  {
    "category": "Best Costume Design (Color)",
    "year": "2002",
    "nominees": [
      "Colleen Atwood"
    ],
    "movies": [
      {
        "title": "Chicago",
        "tmdb_id": 1574,
        "imdb_id": "tt0299658"
      }
    ],
    "won": true
  },
  {
    "category": "Best Costume Design (Color)",
    "year": "2002",
    "nominees": [
      "Julie Weiss"
    ],
    "movies": [
      {
        "title": "Frida",
        "tmdb_id": 1360,
        "imdb_id": "tt0120679"
      }
    ],
    "won": false
  },
  {
    "category": "Best Costume Design (Color)",
    "year": "2002",
    "nominees": [
      "Sandy Powell"
    ],
    "movies": [
      {
        "title": "Gangs of New York",
        "tmdb_id": 3131,
        "imdb_id": "tt0217505"
      }
    ],
    "won": false
  },
  {
    "category": "Best Costume Design (Color)",
    "year": "2002",
    "nominees": [
      "Ann Roth"
    ],
    "movies": [
      {
        "title": "The Hours",
        "tmdb_id": 590,
        "imdb_id": "tt0274558"
      }
    ],
    "won": false
  },
  {
    "category": "Best Costume Design (Color)",
    "year": "2002",
    "nominees": [
      "Anna B. Sheppard"
    ],
    "movies": [
      {
        "title": "The Pianist",
        "tmdb_id": 423,
        "imdb_id": "tt0253474"
      }
    ],
    "won": false
  }
]